{
    "BPM": 86.1328125,
    "beats": [
        {
            "locations": 0,
            "time": 0
        },
        {
            "locations": 2,
            "time": 0
        },
        {
            "locations": 3,
            "time": 0.8937083333333333
        },
        {
            "locations": 2,
            "time": 1.8357708333333334
        },
        {
            "locations": 3,
            "time": 2.5666875
        },
        {
            "locations": 3,
            "time": 3.2689999999999997
        },
        {
            "locations": 2,
            "time": 4.155625
        },
        {
            "locations": 3,
            "time": 4.8943125
        },
        {
            "locations": 2,
            "time": 5.600458333333333
        },
        {
            "locations": 2,
            "time": 6.298791666666666
        },
        {
            "locations": 3,
            "time": 7.026
        },
        {
            "locations": 3,
            "time": 7.771520833333333
        },
        {
            "locations": 2,
            "time": 8.469229166666667
        },
        {
            "locations": 3,
            "time": 9.171375
        },
        {
            "locations": 2,
            "time": 9.8685625
        },
        {
            "locations": 3,
            "time": 10.567166666666667
        },
        {
            "locations": 3,
            "time": 11.2711875
        },
        {
            "locations": 3,
            "time": 11.970645833333332
        },
        {
            "locations": 2,
            "time": 12.675729166666667
        },
        {
            "locations": 3,
            "time": 13.378208333333333
        },
        {
            "locations": 3,
            "time": 14.085145833333334
        },
        {
            "locations": 3,
            "time": 14.7926875
        },
        {
            "locations": 2,
            "time": 15.505291666666666
        },
        {
            "locations": 2,
            "time": 16.202895833333333
        },
        {
            "locations": 2,
            "time": 16.9000625
        },
        {
            "locations": 2,
            "time": 17.598291666666665
        },
        {
            "locations": 3,
            "time": 18.302875
        },
        {
            "locations": 2,
            "time": 18.999958333333332
        },
        {
            "locations": 2,
            "time": 19.7025625
        },
        {
            "locations": 3,
            "time": 20.407333333333334
        },
        {
            "locations": 2,
            "time": 21.10408333333333
        },
        {
            "locations": 2,
            "time": 21.811104166666667
        },
        {
            "locations": 2,
            "time": 22.51427083333333
        },
        {
            "locations": 3,
            "time": 23.21664583333333
        },
        {
            "locations": 3,
            "time": 23.916520833333333
        },
        {
            "locations": 3,
            "time": 24.6141875
        },
        {
            "locations": 3,
            "time": 25.3133125
        },
        {
            "locations": 2,
            "time": 26.0130625
        },
        {
            "locations": 3,
            "time": 26.712333333333333
        },
        {
            "locations": 2,
            "time": 27.48195833333333
        },
        {
            "locations": 3,
            "time": 28.182479166666667
        },
        {
            "locations": 3,
            "time": 32.41320833333333
        },
        {
            "locations": 3,
            "time": 49.82752083333333
        },
        {
            "locations": 2,
            "time": 50.52558333333333
        },
        {
            "locations": 2,
            "time": 51.224125
        },
        {
            "locations": 3,
            "time": 51.93864583333333
        },
        {
            "locations": 3,
            "time": 52.648375
        },
        {
            "locations": 2,
            "time": 53.37739583333333
        },
        {
            "locations": 2,
            "time": 54.079125
        },
        {
            "locations": 3,
            "time": 54.77964583333333
        },
        {
            "locations": 3,
            "time": 55.476375
        },
        {
            "locations": 2,
            "time": 56.20589583333333
        },
        {
            "locations": 2,
            "time": 57.03189583333333
        },
        {
            "locations": 3,
            "time": 57.94933333333333
        },
        {
            "locations": 3,
            "time": 58.957854166666664
        },
        {
            "locations": 3,
            "time": 61.367666666666665
        },
        {
            "locations": 3,
            "time": 62.065374999999996
        },
        {
            "locations": 3,
            "time": 62.832875
        },
        {
            "locations": 3,
            "time": 63.535979166666664
        },
        {
            "locations": 3,
            "time": 64.33033333333333
        },
        {
            "locations": 3,
            "time": 65.02783333333333
        },
        {
            "locations": 2,
            "time": 65.73975
        },
        {
            "locations": 3,
            "time": 66.43964583333333
        },
        {
            "locations": 2,
            "time": 67.48791666666666
        },
        {
            "locations": 2,
            "time": 68.1934375
        },
        {
            "locations": 2,
            "time": 68.91645833333332
        },
        {
            "locations": 2,
            "time": 69.61695833333333
        },
        {
            "locations": 3,
            "time": 70.31454166666667
        },
        {
            "locations": 3,
            "time": 71.01118749999999
        },
        {
            "locations": 2,
            "time": 71.70877083333333
        },
        {
            "locations": 2,
            "time": 72.4309375
        },
        {
            "locations": 3,
            "time": 73.13154166666666
        },
        {
            "locations": 3,
            "time": 73.83004166666666
        },
        {
            "locations": 2,
            "time": 74.53060416666666
        },
        {
            "locations": 2,
            "time": 75.23289583333333
        },
        {
            "locations": 3,
            "time": 75.93002083333333
        },
        {
            "locations": 2,
            "time": 76.62825
        },
        {
            "locations": 2,
            "time": 77.333125
        },
        {
            "locations": 3,
            "time": 78.7161875
        },
        {
            "locations": 2,
            "time": 79.41960416666666
        },
        {
            "locations": 2,
            "time": 80.11629166666667
        },
        {
            "locations": 3,
            "time": 80.81404166666667
        },
        {
            "locations": 2,
            "time": 81.5119375
        },
        {
            "locations": 3,
            "time": 82.21004166666667
        },
        {
            "locations": 2,
            "time": 82.92095833333333
        },
        {
            "locations": 2,
            "time": 83.66729166666667
        },
        {
            "locations": 2,
            "time": 84.36472916666666
        },
        {
            "locations": 3,
            "time": 85.06366666666666
        },
        {
            "locations": 3,
            "time": 85.7631875
        },
        {
            "locations": 2,
            "time": 86.46708333333333
        },
        {
            "locations": 2,
            "time": 87.16777083333334
        },
        {
            "locations": 2,
            "time": 87.86645833333333
        },
        {
            "locations": 2,
            "time": 88.5630625
        },
        {
            "locations": 3,
            "time": 89.2723125
        },
        {
            "locations": 2,
            "time": 89.9744375
        },
        {
            "locations": 3,
            "time": 90.67468749999999
        },
        {
            "locations": 2,
            "time": 91.37260416666666
        },
        {
            "locations": 3,
            "time": 92.07516666666666
        },
        {
            "locations": 2,
            "time": 92.77195833333333
        },
        {
            "locations": 3,
            "time": 93.48470833333333
        },
        {
            "locations": 3,
            "time": 94.40054166666667
        },
        {
            "locations": 3,
            "time": 95.32954166666666
        },
        {
            "locations": 3,
            "time": 105.78385416666666
        },
        {
            "locations": 2,
            "time": 106.50139583333333
        },
        {
            "locations": 2,
            "time": 107.22891666666666
        },
        {
            "locations": 3,
            "time": 107.94816666666667
        },
        {
            "locations": 2,
            "time": 108.77995833333333
        },
        {
            "locations": 3,
            "time": 109.49502083333333
        },
        {
            "locations": 2,
            "time": 110.2290625
        },
        {
            "locations": 2,
            "time": 110.92839583333333
        },
        {
            "locations": 3,
            "time": 111.6275
        },
        {
            "locations": 2,
            "time": 112.34112499999999
        },
        {
            "locations": 2,
            "time": 113.05391666666667
        },
        {
            "locations": 2,
            "time": 114.24510416666666
        },
        {
            "locations": 2,
            "time": 115.09822916666667
        },
        {
            "locations": 2,
            "time": 116.94839583333334
        },
        {
            "locations": 2,
            "time": 117.65579166666666
        },
        {
            "locations": 3,
            "time": 118.35814583333332
        },
        {
            "locations": 2,
            "time": 119.07260416666666
        },
        {
            "locations": 3,
            "time": 119.77164583333332
        },
        {
            "locations": 2,
            "time": 120.67372916666666
        },
        {
            "locations": 2,
            "time": 121.38677083333333
        },
        {
            "locations": 3,
            "time": 122.10635416666666
        },
        {
            "locations": 3,
            "time": 122.80770833333332
        },
        {
            "locations": 2,
            "time": 123.60508333333333
        },
        {
            "locations": 2,
            "time": 124.30445833333333
        },
        {
            "locations": 2,
            "time": 125.003125
        },
        {
            "locations": 3,
            "time": 125.7078125
        },
        {
            "locations": 2,
            "time": 126.407125
        },
        {
            "locations": 3,
            "time": 127.10404166666666
        },
        {
            "locations": 2,
            "time": 127.80779166666666
        },
        {
            "locations": 2,
            "time": 128.5375625
        },
        {
            "locations": 3,
            "time": 129.23683333333332
        },
        {
            "locations": 3,
            "time": 129.93402083333334
        },
        {
            "locations": 2,
            "time": 130.63760416666665
        },
        {
            "locations": 2,
            "time": 131.33758333333333
        },
        {
            "locations": 3,
            "time": 132.0341875
        },
        {
            "locations": 2,
            "time": 132.734125
        },
        {
            "locations": 2,
            "time": 133.44412499999999
        },
        {
            "locations": 2,
            "time": 134.18991666666668
        },
        {
            "locations": 3,
            "time": 134.89935416666665
        },
        {
            "locations": 3,
            "time": 135.60154166666666
        },
        {
            "locations": 2,
            "time": 136.29958333333332
        },
        {
            "locations": 3,
            "time": 137.01314583333334
        },
        {
            "locations": 3,
            "time": 137.71154166666668
        },
        {
            "locations": 3,
            "time": 138.40885416666666
        },
        {
            "locations": 2,
            "time": 139.21629166666665
        },
        {
            "locations": 3,
            "time": 139.913375
        },
        {
            "locations": 2,
            "time": 140.61075
        },
        {
            "locations": 3,
            "time": 141.35666666666665
        },
        {
            "locations": 2,
            "time": 142.05895833333332
        },
        {
            "locations": 2,
            "time": 142.7894375
        },
        {
            "locations": 2,
            "time": 143.48891666666665
        },
        {
            "locations": 2,
            "time": 144.27058333333332
        },
        {
            "locations": 2,
            "time": 144.97108333333333
        },
        {
            "locations": 3,
            "time": 145.88183333333333
        },
        {
            "locations": 3,
            "time": 146.582875
        },
        {
            "locations": 3,
            "time": 147.3088125
        },
        {
            "locations": 3,
            "time": 148.06170833333334
        },
        {
            "locations": 3,
            "time": 148.80064583333333
        },
        {
            "locations": 2,
            "time": 149.50310416666667
        },
        {
            "locations": 2,
            "time": 150.21191666666667
        },
        {
            "locations": 3,
            "time": 150.90952083333332
        },
        {
            "locations": 2,
            "time": 151.61041666666665
        },
        {
            "locations": 3,
            "time": 152.3117083333333
        },
        {
            "locations": 2,
            "time": 153.01760416666667
        },
        {
            "locations": 3,
            "time": 153.7171875
        },
        {
            "locations": 2,
            "time": 154.41379166666667
        },
        {
            "locations": 2,
            "time": 155.11039583333334
        },
        {
            "locations": 2,
            "time": 155.81339583333332
        },
        {
            "locations": 2,
            "time": 156.51422916666667
        },
        {
            "locations": 3,
            "time": 157.2816875
        },
        {
            "locations": 3,
            "time": 157.98054166666665
        },
        {
            "locations": 2,
            "time": 158.67941666666667
        },
        {
            "locations": 3,
            "time": 159.37687499999998
        },
        {
            "locations": 3,
            "time": 160.086875
        },
        {
            "locations": 3,
            "time": 160.78666666666666
        },
        {
            "locations": 3,
            "time": 161.52216666666666
        },
        {
            "locations": 2,
            "time": 162.2274375
        },
        {
            "locations": 3,
            "time": 162.92464583333333
        },
        {
            "locations": 2,
            "time": 163.62212499999998
        },
        {
            "locations": 2,
            "time": 164.31945833333333
        },
        {
            "locations": 3,
            "time": 165.01620833333334
        },
        {
            "locations": 3,
            "time": 165.71502083333334
        },
        {
            "locations": 2,
            "time": 166.41460416666666
        },
        {
            "locations": 2,
            "time": 167.11329166666667
        },
        {
            "locations": 2,
            "time": 167.81125
        },
        {
            "locations": 2,
            "time": 168.50989583333333
        },
        {
            "locations": 3,
            "time": 169.2065
        },
        {
            "locations": 3,
            "time": 169.90547916666665
        },
        {
            "locations": 3,
            "time": 170.605
        },
        {
            "locations": 3,
            "time": 171.3061875
        },
        {
            "locations": 2,
            "time": 172.00389583333333
        },
        {
            "locations": 3,
            "time": 172.71164583333334
        },
        {
            "locations": 2,
            "time": 173.42391666666666
        },
        {
            "locations": 2,
            "time": 174.13108333333332
        },
        {
            "locations": 3,
            "time": 174.842875
        },
        {
            "locations": 3,
            "time": 175.5426875
        },
        {
            "locations": 3,
            "time": 176.24002083333332
        },
        {
            "locations": 2,
            "time": 176.93822916666667
        },
        {
            "locations": 2,
            "time": 177.64241666666666
        },
        {
            "locations": 2,
            "time": 178.34645833333332
        },
        {
            "locations": 3,
            "time": 179.04654166666666
        },
        {
            "locations": 2,
            "time": 179.7455625
        },
        {
            "locations": 3,
            "time": 180.44614583333333
        },
        {
            "locations": 3,
            "time": 181.14452083333333
        },
        {
            "locations": 2,
            "time": 181.841625
        },
        {
            "locations": 3,
            "time": 182.53835416666666
        },
        {
            "locations": 3,
            "time": 183.23964583333333
        },
        {
            "locations": 2,
            "time": 183.93939583333332
        },
        {
            "locations": 2,
            "time": 184.71658333333332
        },
        {
            "locations": 2,
            "time": 185.41325
        },
        {
            "locations": 2,
            "time": 186.11072916666666
        },
        {
            "locations": 3,
            "time": 186.81104166666665
        },
        {
            "locations": 2,
            "time": 187.52191666666667
        },
        {
            "locations": 2,
            "time": 188.27577083333333
        },
        {
            "locations": 3,
            "time": 188.98154166666666
        },
        {
            "locations": 2,
            "time": 189.68125
        },
        {
            "locations": 3,
            "time": 190.39564583333333
        },
        {
            "locations": 2,
            "time": 191.09277083333333
        },
        {
            "locations": 2,
            "time": 191.7949375
        },
        {
            "locations": 2,
            "time": 192.5340625
        },
        {
            "locations": 3,
            "time": 193.2406875
        },
        {
            "locations": 3,
            "time": 193.94202083333332
        },
        {
            "locations": 2,
            "time": 194.64677083333333
        }
    ],
    "name": "wav\\lights.wav"
}